pygridsio/__init__.py
pygridsio/IO/AscZmapIO.py
pygridsio/IO/__init__.py
pygridsio/IO/geotiffIO.py
pygridsio/IO/gocad.py
pygridsio/IO/grid_to_xarray.py
pygridsio/IO/main_IO_functions.py
pygridsio/IO/netcdfIO.py
pygridsio/IO/voxet.py
pygridsio/grid_functions/__init__.py
pygridsio/grid_functions/grid_operations.py
pygridsio/grid_functions/grid_plotting.py
pygridsio/resources/__init__.py
pygridsio/resources/netherlands_shapefile/2019_provinciegrenzen_kustlijn.cpg
pygridsio/resources/netherlands_shapefile/2019_provinciegrenzen_kustlijn.dbf
pygridsio/resources/netherlands_shapefile/2019_provinciegrenzen_kustlijn.prj
pygridsio/resources/netherlands_shapefile/2019_provinciegrenzen_kustlijn.shp
pygridsio/resources/netherlands_shapefile/2019_provinciegrenzen_kustlijn.shx
pygridsio/resources/netherlands_shapefile/__init__.py
pygridsio/resources/netherlands_shapefile/shapefile_plot_util.py
pygridsio-1.1.3.dist-info/licenses/LICENSE
pygridsio-1.1.3.dist-info/METADATA
pygridsio-1.1.3.dist-info/WHEEL
pygridsio-1.1.3.dist-info/top_level.txt
pygridsio-1.1.3.dist-info/RECORD
