Metadata-Version: 2.4
Name: pygridsio
Version: 1.1.3
Summary: This is a utility package to enable IO and plotting for .nc, .tif, .zmap, .asc grid files or xarray objects
Author-email: Hen Brett <hen.brett@tno.nl>
License: Permission is hereby granted, free of charge, to any person obtaining a copy of this software and associated documentation files (the “Software”), to deal in the Software without restriction, including without limitation the rights to use, copy, modify, merge, publish, distribute, sublicense, and/or sell copies of the Software, and to permit persons to whom the Software is furnished to do so, subject to the following conditions:
Requires-Python: >=3.6
License-File: LICENSE
Requires-Dist: numpy
Requires-Dist: pandas
Requires-Dist: pykrige
Requires-Dist: xarray
Requires-Dist: rioxarray
Requires-Dist: netCDF4
Requires-Dist: plotly
Requires-Dist: geopandas
Requires-Dist: matplotlib
Requires-Dist: contextily
Dynamic: license-file
